{
  "nb": 30,
  "ni": 180,
  "mlt": 10000,
  "b_w": [
    279,
    319,
    172,
    352,
    495,
    398,
    283,
    588,
    334,
    178,
    414,
    530,
    377,
    166,
    132,
    491,
    447,
    246,
    295,
    128,
    390,
    228,
    560,
    241,
    621,
    260,
    193,
    312,
    257,
    314
  ],
  "i_w": [
    86,
    30,
    19,
    78,
    82,
    16,
    55,
    93,
    70,
    77,
    49,
    69,
    42,
    55,
    40,
    73,
    81,
    90,
    19,
    22,
    82,
    84,
    62,
    37,
    62,
    46,
    26,
    52,
    41,
    31,
    94,
    75,
    61,
    15,
    12,
    51,
    64,
    47,
    75,
    71,
    27,
    60,
    68,
    89,
    32,
    17,
    46,
    35,
    59,
    73,
    89,
    64,
    78,
    30,
    85,
    85,
    94,
    23,
    22,
    36,
    56,
    27,
    36,
    43,
    51,
    67,
    82,
    57,
    49,
    69,
    26,
    75,
    45,
    90,
    43,
    22,
    96,
    47,
    44,
    98,
    26,
    42,
    28,
    26,
    67,
    57,
    70,
    73,
    56,
    38,
    67,
    59,
    49,
    93,
    39,
    71,
    18,
    56,
    71,
    70,
    96,
    74,
    37,
    68,
    75,
    54,
    42,
    70,
    82,
    54,
    72,
    29,
    49,
    19,
    78,
    74,
    86,
    35,
    76,
    64,
    17,
    64,
    40,
    59,
    57,
    68,
    88,
    94,
    72,
    44,
    32,
    57,
    66,
    41,
    54,
    14,
    79,
    60,
    25,
    55,
    52,
    74,
    77,
    69,
    35,
    97,
    58,
    32,
    62,
    30,
    26,
    43,
    52,
    66,
    22,
    64,
    56,
    93,
    38,
    17,
    83,
    37,
    45,
    29,
    81,
    81,
    45,
    57,
    45,
    87,
    73,
    27,
    36,
    62,
    36,
    12,
    76,
    63,
    47,
    50
  ]
}