{
  "nb": 20,
  "ni": 80,
  "mlt": 10000,
  "b_w": [
    570,
    336,
    820,
    437,
    669,
    681,
    989,
    315,
    113,
    696,
    151,
    378,
    911,
    289,
    133,
    659,
    263,
    192,
    569,
    829
  ],
  "i_w": [
    109,
    32,
    22,
    47,
    183,
    67,
    199,
    110,
    222,
    55,
    143,
    81,
    155,
    101,
    56,
    163,
    152,
    186,
    157,
    209,
    47,
    71,
    139,
    130,
    192,
    78,
    181,
    226,
    147,
    105,
    191,
    109,
    71,
    203,
    90,
    186,
    46,
    127,
    84,
    186,
    174,
    213,
    94,
    116,
    26,
    65,
    193,
    132,
    111,
    115,
    206,
    40,
    183,
    202,
    246,
    181,
    164,
    166,
    35,
    33,
    140,
    134,
    132,
    142,
    54,
    191,
    148,
    69,
    33,
    221,
    138,
    22,
    154,
    143,
    35,
    156,
    91,
    86,
    28,
    130
  ]
}